<?xml version="1.0" encoding="UTF-8"?>
<!DOCTYPE list SYSTEM "skill.dtd">
<list>
	<skill id="2209" levels="1" name="Blessed Scroll: Enchant Armor (A-grade)">
		<set name="icon" value="icon.skill0000"/>
		<set name="target" value="TARGET_NONE"/>
		<set name="skillType" value="NOTUSED"/>
		<set name="operate_type" value="P"/>
	</skill>
	<skill id="2210" levels="1" name="Blessed Scroll: Enchant Armor (B-grade)">
		<set name="icon" value="icon.skill0000"/>
		<set name="ride_state" value="NONE;STRIDER;WYVERN;WOLF"/>
		<set name="magicLevel" value="1"/>
		<set name="magicType" value="SPECIAL"/>
		<set name="target" value="TARGET_NONE"/>
		<set name="skillType" value="NOTDONE"/>
		<set name="operate_type" value="A2"/>
	</skill>
	<skill id="2211" levels="1" name="Blessed Scroll: Enchant Armor (C-grade)">
		<set name="icon" value="icon.skill0000"/>
		<set name="ride_state" value="NONE;STRIDER;WYVERN;WOLF"/>
		<set name="magicLevel" value="1"/>
		<set name="magicType" value="SPECIAL"/>
		<set name="target" value="TARGET_NONE"/>
		<set name="skillType" value="NOTDONE"/>
		<set name="operate_type" value="A2"/>
	</skill>
	<skill id="2212" levels="1" name="Blessed Scroll: Enchant Armor (D-grade)">
		<set name="icon" value="icon.skill0000"/>
		<set name="ride_state" value="NONE;STRIDER;WYVERN;WOLF"/>
		<set name="magicLevel" value="1"/>
		<set name="magicType" value="SPECIAL"/>
		<set name="target" value="TARGET_NONE"/>
		<set name="skillType" value="NOTDONE"/>
		<set name="operate_type" value="A2"/>
	</skill>
	<skill id="2213" levels="15" name="Scroll of Escape: Talking Island Village">
		<table name="#loc">
			-84200;244566;-3728
			46915;51441;-2976
			9723;15576;-4568
			-45208;-112502;-240
			115158;-178170;-880
			-80831;149808;-3040
			-12728;122726;-3112
			15633;142962;-2696
			17860;170191;-3496
			83378;147999;-3400
			105760;113064;-3176
			111388;219331;-3544
			82916;53210;-1488
			85289;16225;-3672
			117052;76884;-2688
		</table>
		<set name="icon" value="icon.skill0000"/>
		<set name="hitTime" value="20000"/>
		<set name="ride_state" value="NONE;STRIDER;WYVERN;WOLF"/>
		<set name="magicLevel" value="1"/>
		<set name="magicType" value="SPECIAL"/>
		<set name="hitCancelTime" value="500"/>
		<set name="loc" value="#loc"/>
		<set name="isHandler" value="true"/>
		<set name="target" value="TARGET_SELF"/>
		<set name="skillType" value="RECALL"/>
		<set name="operate_type" value="A2"/>
	</skill>
</list>