<?xml version="1.0" encoding="UTF-8"?>
<!DOCTYPE list SYSTEM "npc.dtd">
<list>
	<npc id="4308" name="Angel Cat" title="Herald of Love">
		<set name="type" value="Npc"/>
		<set name="ai_type" value="NpcAI"/>
		<set name="collision_height" value="16"/>
		<set name="collision_radius" value="6"/>
		<set name="level" value="70"/>
		<set name="rewardExp" value="0"/>
		<set name="rewardSp" value="0"/>
		<set name="baseHpMax" value="2444"/>
		<set name="baseHpRate" value="1"/>
		<set name="baseHpReg" value="7.5"/>
		<set name="baseMpMax" value="1345"/>
		<set name="baseMpReg" value="2.7"/>
		<set name="baseSTR" value="40"/>
		<set name="baseCON" value="43"/>
		<set name="baseDEX" value="30"/>
		<set name="baseINT" value="21"/>
		<set name="baseMEN" value="10"/>
		<set name="baseWIT" value="20"/>
		<set name="basePCritRate" value="40"/>
		<set name="baseMCritRate" value="50"/>
		<set name="basePAtk" value="688.863725587608"/>
		<set name="basePDef" value="295.91597408024"/>
		<set name="basePAtkSpd" value="253"/>
		<set name="baseMAtk" value="470.404627426724"/>
		<set name="baseMDef" value="216.538467292763"/>
		<set name="baseWalkSpd" value="48"/>
		<set name="baseRunSpd" value="140"/>
		<set name="baseShldDef" value="0"/>
		<set name="baseShldRate" value="0"/>
		<set name="baseAtkRange" value="40"/>
		<set name="baseRandDam" value="30"/>
		<set name="baseAttackType" value="FIST"/>
		<set name="basePHitModify" value="4.75"/>
		<set name="basePAvoidModify" value="0"/>
		<set name="baseHitTimeFactor" value="0.6"/>
		<set name="baseReuseDelay" value="0"/>
		<set name="baseSafeHeight" value="100"/>
		<set name="aggroRange" value="0"/>
		<set name="shots" value="NONE"/>
	</npc>
	<npc id="4309" name="Small Angel Cat" title="Herald of Love">
		<set name="type" value="Npc"/>
		<set name="ai_type" value="NpcAI"/>
		<set name="collision_height" value="15"/>
		<set name="collision_radius" value="8"/>
		<set name="level" value="70"/>
		<set name="rewardExp" value="0"/>
		<set name="rewardRp" value="0"/>
		<set name="rewardSp" value="0"/>
		<set name="baseHpMax" value="8446"/>
		<set name="baseHpRate" value="1"/>
		<set name="baseHpReg" value="7.5"/>
		<set name="baseMpMax" value="2355"/>
		<set name="baseMpReg" value="2.7"/>
		<set name="baseSTR" value="40"/>
		<set name="baseCON" value="43"/>
		<set name="baseDEX" value="30"/>
		<set name="baseINT" value="21"/>
		<set name="baseMEN" value="20"/>
		<set name="baseWIT" value="20"/>
		<set name="basePCritRate" value="40"/>
		<set name="baseMCritRate" value="50"/>
		<set name="basePAtk" value="688.86373"/>
		<set name="basePDef" value="295.91597"/>
		<set name="basePAtkSpd" value="253"/>
		<set name="baseMAtk" value="470.40463"/>
		<set name="baseMDef" value="216.53847"/>
		<set name="baseWalkSpd" value="25"/>
		<set name="baseRunSpd" value="140"/>
		<set name="baseShldDef" value="0"/>
		<set name="baseShldRate" value="0"/>
		<set name="baseAtkRange" value="40"/>
		<set name="baseRandDam" value="30"/>
		<set name="baseAttackType" value="SWORD"/>
		<set name="basePHitModify" value="5"/>
		<set name="basePAvoidModify" value="0"/>
		<set name="baseHitTimeFactor" value="0.6"/>
		<set name="baseReuseDelay" value="0"/>
		<set name="baseSafeHeight" value="100"/>
		<set name="aggroRange" value="0"/>
		<set name="shots" value="NONE"/>
		<set name="castle_id" value="4"/>
	</npc>
</list>